karl_jiang_mcp_demo/__init__.py
karl_jiang_mcp_demo-0.1.4.dist-info/WHEEL
karl_jiang_mcp_demo-0.1.4.dist-info/entry_points.txt
karl_jiang_mcp_demo-0.1.4.dist-info/METADATA
karl_jiang_mcp_demo-0.1.4.dist-info/RECORD
