Metadata-Version: 2.3
Name: karl-jiang-mcp-demo
Version: 0.1.4
Summary: Add your description here
Author: jiangxiaoman
Author-email: jiangxiaoman <jiangxiaoman@cjy.org>
Requires-Dist: mcp[cli]>=1.24.0
Requires-Python: >=3.13
